<?xml version="1.0" encoding="utf-8" ?><!DOCTYPE tv SYSTEM "xmltv.dtd">
<tv generator-info-name="INFRAX">
	<channel id="AE.br">
		<display-name>A&amp;E HD</display-name>
		<icon src="http://cutix.click/logos/tjHaxHl8_o.png" />
	</channel>
	<channel id="AE.br">
		<display-name>A&amp;E SD</display-name>
		<icon src="http://cutix.click/logos/tjHaxHl8_o.png" />
	</channel>
	<channel id="AMC.br">
		<display-name>AMC HD</display-name>
		<icon src="http://cutix.click/logos/vDGikpom_o.png" />
	</channel>
	<channel id="AMC.br">
		<display-name>AMC SD</display-name>
		<icon src="http://cutix.click/logos/vDGikpom_o.png" />
	</channel>
	<channel id="Arte1.br">
		<display-name>Arte 1 HD</display-name>
		<icon src="http://cutix.click/logos/AsZeXT00_o.png" />
	</channel>
	<channel id="Arte1.br">
		<display-name>Arte 1 SD</display-name>
		<icon src="http://cutix.click/logos/AsZeXT00_o.png" />
	</channel>
	<channel id="AXN.br">
		<display-name>AXN HD</display-name>
		<icon src="http://cutix.click/logos/5XqWzSHh_o.png" />
	</channel>
	<channel id="AXN.br">
		<display-name>AXN SD</display-name>
		<icon src="http://cutix.click/logos/5XqWzSHh_o.png" />
	</channel>
	<channel id="br#canal-brasil-hd">
		<display-name>Canal Brasil SD</display-name>
		<icon src="http://cutix.click/logos/QXucCN9Z_o.png" />
	</channel>
	<channel id="br#sony-hd">
		<display-name>Canal Sony HD</display-name>
		<icon src="http://cutix.click/logos/kbbzPGMJ_o.png" />
	</channel>
	<channel id="br#sony-hd">
		<display-name>Canal Sony SD</display-name>
		<icon src="http://cutix.click/logos/kbbzPGMJ_o.png" />
	</channel>
	<channel id="br#cinemax-1">
		<display-name>Cinemax HD</display-name>
		<icon src="http://cutix.click/logos/PzE1qJZ4_o.png" />
	</channel>
	<channel id="br#cinemax-1">
		<display-name>Cinemax SD</display-name>
		<icon src="http://cutix.click/logos/PzE1qJZ4_o.png" />
	</channel>
	<channel id="br#megapix-hd">
		<display-name>Megapix HD</display-name>
		<icon src="http://cutix.click/logos/taPZMx4o_o.png" />
	</channel>
	<channel id="br#megapix-hd">
		<display-name>Megapix SD</display-name>
		<icon src="http://cutix.click/logos/taPZMx4o_o.png" />
	</channel>
	<channel id="br#paramount-brasil-hd">
		<display-name>Paramount HD</display-name>
		<icon src="http://cutix.click/logos/PKZ9ucKc_o.png" />
	</channel>
	<channel id="br#paramount-brasil-hd">
		<display-name>Paramount SD</display-name>
		<icon src="http://cutix.click/logos/PKZ9ucKc_o.png" />
	</channel>
	<channel id="br#space-hd">
		<display-name>Space HD</display-name>
		<icon src="http://cutix.click/logos/A8PCst0b_o.png" />
	</channel>
	<channel id="br#space-hd">
		<display-name>Space SD</display-name>
		<icon src="http://cutix.click/logos/A8PCst0b_o.png" />
	</channel>
	<channel id="br#fox-hd">
		<display-name>Star Channel HD</display-name>
		<icon src="https://imagizer.imageshack.com/v2/150x100q90/922/p6i9NV.png" />
	</channel>
	<channel id="br#fox-hd">
		<display-name>Star Channel SD</display-name>
		<icon src="https://imagizer.imageshack.com/v2/150x100q90/922/p6i9NV.png" />
	</channel>
	<channel id="br#studio-universal-hd">
		<display-name>Studio Universal HD</display-name>
		<icon src="http://cutix.click/logos/PUZoFdtE_o.png" />
	</channel>
	<channel id="br#studio-universal-hd">
		<display-name>Studio Universal SD</display-name>
		<icon src="http://cutix.click/logos/PUZoFdtE_o.png" />
	</channel>
	<channel id="TCM.br">
		<display-name>TCM  HD</display-name>
		<icon src="http://cutix.click/logos/pJquJCtz_o.png" />
	</channel>
	<channel id="br#tlc-hd">
		<display-name>TLC HD</display-name>
		<icon src="http://cutix.click/logos/WAMcsVqF_o.png" />
	</channel>
	<channel id="br#tnt-hd">
		<display-name>TNT HD</display-name>
		<icon src="http://cutix.click/logos/NXOXkfYe_o.png" />
	</channel>
	<channel id="br#tnt-hd">
		<display-name>TNT SD</display-name>
		<icon src="http://cutix.click/logos/NXOXkfYe_o.png" />
	</channel>
	<channel id="br#tnt-series-hd">
		<display-name>TNT Séries SD</display-name>
		<icon src="http://cutix.click/logos/E7QDkpUK_o.png" />
	</channel>
	<channel id="UniversalTV.br">
		<display-name>Universal TV HD</display-name>
		<icon src="http://cutix.click/logos/Nj8XRd5W_o.png" />
	</channel>
	<channel id="UniversalTV.br">
		<display-name>Universal TV SD</display-name>
		<icon src="http://cutix.click/logos/Nj8XRd5W_o.png" />
	</channel>
	<channel id="br#warner-channel-hd">
		<display-name>Warner HD</display-name>
		<icon src="http://157.254.54.188/filmeseseries/warnerchannel.png" />
	</channel>
	<channel id="br#warner-channel-hd">
		<display-name>Warner SD</display-name>
		<icon src="http://157.254.54.188/filmeseseries/warnerchannel.png" />
	</channel>
	<channel id="br#tnt-series-hd">
		<display-name>TNT Séries HD</display-name>
		<icon src="http://cutix.click/logos/E7QDkpUK_o.png" />
	</channel>
	<channel id="AE.br">
		<display-name>A&amp;E FHD</display-name>
		<icon src="http://cutix.click/logos/tjHaxHl8_o.png" />
	</channel>
	<channel id="AMC.br">
		<display-name>AMC FHD</display-name>
		<icon src="http://cutix.click/logos/vDGikpom_o.png" />
	</channel>
	<channel id="Arte1.br">
		<display-name>Arte 1 FHD</display-name>
		<icon src="http://cutix.click/logos/AsZeXT00_o.png" />
	</channel>
	<channel id="AXN.br">
		<display-name>AXN FHD</display-name>
		<icon src="http://cutix.click/logos/5XqWzSHh_o.png" />
	</channel>
	<channel id="br#canal-brasil-hd">
		<display-name>Canal Brasil FHD</display-name>
		<icon src="http://cutix.click/logos/QXucCN9Z_o.png" />
	</channel>
	<channel id="br#sony-hd">
		<display-name>Canal Sony FHD</display-name>
		<icon src="http://cutix.click/logos/kbbzPGMJ_o.png" />
	</channel>
	<channel id="br#cinemax-1">
		<display-name>Cinemax FHD</display-name>
		<icon src="http://cutix.click/logos/PzE1qJZ4_o.png" />
	</channel>
	<channel id="br#megapix-hd">
		<display-name>Megapix FHD</display-name>
		<icon src="http://cutix.click/logos/taPZMx4o_o.png" />
	</channel>
	<channel id="br#paramount-brasil-hd">
		<display-name>Paramount FHD</display-name>
		<icon src="http://cutix.click/logos/PKZ9ucKc_o.png" />
	</channel>
	<channel id="br#space-hd">
		<display-name>Space FHD</display-name>
		<icon src="http://cutix.click/logos/A8PCst0b_o.png" />
	</channel>
	<channel id="br#studio-universal-hd">
		<display-name>Studio Universal FHD</display-name>
		<icon src="http://cutix.click/logos/PUZoFdtE_o.png" />
	</channel>
	<channel id="br#tnt-hd">
		<display-name>TNT FHD</display-name>
		<icon src="http://cutix.click/logos/NXOXkfYe_o.png" />
	</channel>
	<channel id="br#tnt-series-hd">
		<display-name>TNT Séries FHD</display-name>
		<icon src="http://cutix.click/logos/E7QDkpUK_o.png" />
	</channel>
	<channel id="UniversalTV.br">
		<display-name>Universal TV FHD</display-name>
		<icon src="http://cutix.click/logos/Nj8XRd5W_o.png" />
	</channel>
	<channel id="br#warner-channel-hd">
		<display-name>Warner FHD</display-name>
		<icon src="http://157.254.54.188/filmeseseries/warnerchannel.png" />
	</channel>
	<channel id="AnimalPlanet.br">
		<display-name>Animal Planet HD</display-name>
		<icon src="http://cutix.click/logos/M99ieJuG_o.png" />
	</channel>
	<channel id="AnimalPlanet.br">
		<display-name>Animal Planet SD</display-name>
		<icon src="http://cutix.click/logos/M99ieJuG_o.png" />
	</channel>
	<channel id="br#fish-tv-hd">
		<display-name>Fish TV HD</display-name>
		<icon src="http://cutix.click/logos/8OUuEpbB_o.png" />
	</channel>
	<channel id="br#fish-tv-hd">
		<display-name>Fish TV SD</display-name>
		<icon src="http://cutix.click/logos/8OUuEpbB_o.png" />
	</channel>
	<channel id="br#h2-hd">
		<display-name>H2 HD</display-name>
		<icon src="http://cutix.click/logos/5u0u6eDK_o.png" />
	</channel>
	<channel id="br#h2-hd">
		<display-name>H2 SD</display-name>
		<icon src="http://cutix.click/logos/5u0u6eDK_o.png" />
	</channel>
	<channel id="History2.br">
		<display-name>History 2 HD</display-name>
		<icon src="http://cutix.click/logos/5u0u6eDK_o.png" />
	</channel>
	<channel id="History2.br">
		<display-name>History 2 SD</display-name>
		<icon src="http://cutix.click/logos/5u0u6eDK_o.png" />
	</channel>
	<channel id="br#history-channel-hd">
		<display-name>History Channel HD</display-name>
		<icon src="http://cutix.click/logos/WfGLRlos_o.png" />
	</channel>
	<channel id="br#history-channel-hd">
		<display-name>History Channel SD</display-name>
		<icon src="http://cutix.click/logos/WfGLRlos_o.png" />
	</channel>
	<channel id="br#prime-box-brazil-hd">
		<display-name>Prime Box Brazil HD</display-name>
	</channel>
	<channel id="br#prime-box-brazil-hd">
		<display-name>Prime Box Brazil SD</display-name>
		<icon src="http://imagizer.imageshack.us/v2/640x480q90/922/llUm4U.png" />
	</channel>
	<channel id="AnimalPlanet.br">
		<display-name>Animal Planet FHD</display-name>
		<icon src="http://cutix.click/logos/M99ieJuG_o.png" />
	</channel>
	<channel id="br#fish-tv-hd">
		<display-name>Fish TV FHD</display-name>
		<icon src="http://cutix.click/logos/8OUuEpbB_o.png" />
	</channel>
	<channel id="br#history-channel-hd">
		<display-name>History Channel FHD</display-name>
		<icon src="http://cutix.click/logos/WfGLRlos_o.png" />
	</channel>
	<channel id="br#h2-hd">
		<display-name>H2 FHD</display-name>
		<icon src="http://cutix.click/logos/5u0u6eDK_o.png" />
	</channel>
	<channel id="br#prime-box-brazil-hd">
		<display-name>Prime Box Brazil FHD</display-name>
		<icon src="http://imagizer.imageshack.us/v2/640x480q90/922/llUm4U.png" />
	</channel>
	<channel id="History2.br">
		<display-name>History 2 FHD</display-name>
		<icon src="http://cutix.click/logos/5u0u6eDK_o.png" />
	</channel>
	<channel id="br#telecine-action-hd">
		<display-name>Telecine Action HD</display-name>
		<icon src="http://cutix.click/logos/GnaJaVwm_o.png" />
	</channel>
	<channel id="br#telecine-action-hd">
		<display-name>Telecine Action SD</display-name>
		<icon src="http://cutix.click/logos/GnaJaVwm_o.png" />
	</channel>
	<channel id="br#telecine-cult-hd">
		<display-name>Telecine Cult HD</display-name>
		<icon src="http://cutix.click/logos/bf0MqOkD_o.png" />
	</channel>
	<channel id="br#telecine-cult-hd">
		<display-name>Telecine Cult SD</display-name>
		<icon src="http://cutix.click/logos/bf0MqOkD_o.png" />
	</channel>
	<channel id="br#telecine-fun-hd">
		<display-name>Telecine Fun SD</display-name>
		<icon src="http://cutix.click/logos/OnTjFGgJ_o.png" />
	</channel>
	<channel id="br#telecine-pipoca-hd">
		<display-name>Telecine Pipoca HD</display-name>
		<icon src="http://cutix.click/logos/4K9WNUDh_o.png" />
	</channel>
	<channel id="br#telecine-pipoca-hd">
		<display-name>Telecine Pipoca SD</display-name>
		<icon src="http://cutix.click/logos/4K9WNUDh_o.png" />
	</channel>
	<channel id="br#telecine-premium-hd">
		<display-name>Telecine Premium HD</display-name>
		<icon src="http://cutix.click/logos/BYMM8aSx_o.png" />
	</channel>
	<channel id="br#telecine-premium-hd">
		<display-name>Telecine Premium SD</display-name>
		<icon src="http://cutix.click/logos/BYMM8aSx_o.png" />
	</channel>
	<channel id="br#telecine-touch-hd">
		<display-name>Telecine Touch HD</display-name>
		<icon src="http://cutix.click/logos/diZl7CGP_o.png" />
	</channel>
	<channel id="br#telecine-touch-hd">
		<display-name>Telecine Touch SD</display-name>
		<icon src="http://cutix.click/logos/diZl7CGP_o.png" />
	</channel>
	<channel id="br#telecine-action-hd">
		<display-name>Telecine Action FHD</display-name>
		<icon src="http://cutix.click/logos/GnaJaVwm_o.png" />
	</channel>
	<channel id="br#telecine-cult-hd">
		<display-name>Telecine Cult FHD</display-name>
		<icon src="http://cutix.click/logos/bf0MqOkD_o.png" />
	</channel>
	<channel id="br#telecine-fun-hd">
		<display-name>Telecine Fun FHD</display-name>
		<icon src="http://cutix.click/logos/OnTjFGgJ_o.png" />
	</channel>
	<channel id="br#telecine-pipoca-hd">
		<display-name>Telecine Pipoca FHD</display-name>
		<icon src="http://cutix.click/logos/4K9WNUDh_o.png" />
	</channel>
	<channel id="br#telecine-premium-hd">
		<display-name>Telecine Premium FHD</display-name>
		<icon src="http://cutix.click/logos/BYMM8aSx_o.png" />
	</channel>
	<channel id="br#telecine-touch-hd">
		<display-name>Telecine Touch FHD</display-name>
		<icon src="http://cutix.click/logos/diZl7CGP_o.png" />
	</channel>
	<channel id="br#telecine-fun-hd">
		<display-name>Telecine Fun HD</display-name>
		<icon src="http://cutix.click/logos/OnTjFGgJ_o.png" />
	</channel>
	<channel id="br#hbo-2">
		<display-name>HBO 2 SD</display-name>
		<icon src="http://cutix.click/logos/15c3Cu7F_o.png" />
	</channel>
	<channel id="HBOFamily.br">
		<display-name>HBO Family HD</display-name>
		<icon src="http://cutix.click/logos/gPbwkcb8_o.png" />
	</channel>
	<channel id="HBOFamily.br">
		<display-name>HBO Family SD</display-name>
		<icon src="http://cutix.click/logos/gPbwkcb8_o.png" />
	</channel>
	<channel id="br#hbo-hd">
		<display-name>HBO HD</display-name>
		<icon src="http://cutix.click/logos/MxFExDB9_o.png" />
	</channel>
	<channel id="br#max">
		<display-name>HBO Mundi HD</display-name>
		<icon src="http://cutix.click/logos/Bant1u0d_o.png" />
	</channel>
	<channel id="br#max">
		<display-name>HBO Mundi SD</display-name>
		<icon src="http://cutix.click/logos/Bant1u0d_o.png" />
	</channel>
	<channel id="HBOPop.br">
		<display-name>HBO Pop HD</display-name>
		<icon src="http://cutix.click/logos/XwfImJZy_o.png" />
	</channel>
	<channel id="HBOPop.br">
		<display-name>HBO Pop SD</display-name>
		<icon src="http://cutix.click/logos/XwfImJZy_o.png" />
	</channel>
	<channel id="br#hbo-hd">
		<display-name>HBO SD</display-name>
		<icon src="http://cutix.click/logos/MxFExDB9_o.png" />
	</channel>
	<channel id="br#hbo-signature-1">
		<display-name>HBO Signature HD</display-name>
		<icon src="http://cutix.click/logos/0IDs4wcG_o.png" />
	</channel>
	<channel id="br#hbo-signature-1">
		<display-name>HBO Signature SD</display-name>
		<icon src="http://cutix.click/logos/0IDs4wcG_o.png" />
	</channel>
	<channel id="br#max-prime">
		<display-name>HBO Xtreme HD</display-name>
		<icon src="http://cutix.click/logos/O7jlBA1I_o.png" />
	</channel>
	<channel id="br#max-prime">
		<display-name>HBO Xtreme SD</display-name>
		<icon src="http://cutix.click/logos/O7jlBA1I_o.png" />
	</channel>
	<channel id="br#hbo-hd">
		<display-name>HBO+ HD</display-name>
		<icon src="http://cutix.click/logos/JwXMJrz4_o.png" />
	</channel>
	<channel id="br#hbo-hd">
		<display-name>HBO+ SD</display-name>
		<icon src="http://cutix.click/logos/JwXMJrz4_o.png" />
	</channel>
	<channel id="br#hbo-2">
		<display-name>HBO 2 HD</display-name>
		<icon src="http://cutix.click/logos/15c3Cu7F_o.png" />
	</channel>
	<channel id="br#hbo-hd">
		<display-name>HBO FHD</display-name>
		<icon src="http://cutix.click/logos/MxFExDB9_o.png" />
	</channel>
	<channel id="br#hbo-2">
		<display-name>HBO 2 FHD</display-name>
		<icon src="http://cutix.click/logos/15c3Cu7F_o.png" />
	</channel>
	<channel id="HBOFamily.br">
		<display-name>HBO Family FHD</display-name>
		<icon src="http://cutix.click/logos/gPbwkcb8_o.png" />
	</channel>
	<channel id="br#max">
		<display-name>HBO Mundi FHD</display-name>
		<icon src="http://cutix.click/logos/Bant1u0d_o.png" />
	</channel>
	<channel id="HBOPop.br">
		<display-name>HBO POP FHD</display-name>
		<icon src="http://cutix.click/logos/XwfImJZy_o.png" />
	</channel>
	<channel id="br#hbo-signature-1">
		<display-name>HBO Signature FHD</display-name>
		<icon src="http://cutix.click/logos/0IDs4wcG_o.png" />
	</channel>
	<channel id="br#max-prime">
		<display-name>HBO Xtreme FHD</display-name>
		<icon src="http://cutix.click/logos/O7jlBA1I_o.png" />
	</channel>
	<channel id="br#hbo-hd">
		<display-name>HBO+ FHD</display-name>
		<icon src="http://cutix.click/logos/JwXMJrz4_o.png" />
	</channel>
	<channel id="br#premiere-2">
		<display-name>Premiere 2 HD</display-name>
		<icon src="http://cutix.click/logos/ehtIUqjk_o.png" />
	</channel>
	<channel id="br#premiere-2">
		<display-name>Premiere 2 SD</display-name>
		<icon src="http://cutix.click/logos/ehtIUqjk_o.png" />
	</channel>
	<channel id="br#premiere-3">
		<display-name>Premiere 3 HD</display-name>
		<icon src="http://cutix.click/logos/ehtIUqjk_o.png" />
	</channel>
	<channel id="br#premiere-3">
		<display-name>Premiere 3 SD</display-name>
		<icon src="http://cutix.click/logos/ehtIUqjk_o.png" />
	</channel>
	<channel id="br#premiere-4">
		<display-name>Premiere 4 HD</display-name>
		<icon src="http://cutix.click/logos/ehtIUqjk_o.png" />
	</channel>
	<channel id="br#premiere-4">
		<display-name>Premiere 4 SD</display-name>
		<icon src="http://cutix.click/logos/ehtIUqjk_o.png" />
	</channel>
	<channel id="br#premiere-5-hd">
		<display-name>Premiere 5 HD</display-name>
		<icon src="http://cutix.click/logos/ehtIUqjk_o.png" />
	</channel>
	<channel id="br#premiere-5-hd">
		<display-name>Premiere 5 SD</display-name>
		<icon src="http://cutix.click/logos/ehtIUqjk_o.png" />
	</channel>
	<channel id="br#premiere-6">
		<display-name>Premiere 6 HD</display-name>
		<icon src="http://cutix.click/logos/ehtIUqjk_o.png" />
	</channel>
	<channel id="br#premiere-6">
		<display-name>Premiere 6 SD</display-name>
		<icon src="http://cutix.click/logos/ehtIUqjk_o.png" />
	</channel>
	<channel id="br#premiere-7">
		<display-name>Premiere 7 HD</display-name>
		<icon src="http://cutix.click/logos/ehtIUqjk_o.png" />
	</channel>
	<channel id="br#premiere-7">
		<display-name>Premiere 7 SD</display-name>
		<icon src="http://cutix.click/logos/ehtIUqjk_o.png" />
	</channel>
	<channel id="br#premiere-clubes-hd">
		<display-name>Premiere Clubes HD</display-name>
		<icon src="http://cutix.click/logos/ehtIUqjk_o.png" />
	</channel>
	<channel id="br#premiere-clubes-hd">
		<display-name>Premiere Clubes SD</display-name>
		<icon src="http://cutix.click/logos/ehtIUqjk_o.png" />
	</channel>
	<channel id="br#premiere-2">
		<display-name>Premiere 2 FHD</display-name>
		<icon src="http://cutix.click/logos/ehtIUqjk_o.png" />
	</channel>
	<channel id="br#premiere-3">
		<display-name>Premiere 3 FHD</display-name>
		<icon src="http://cutix.click/logos/ehtIUqjk_o.png" />
	</channel>
	<channel id="br#premiere-4">
		<display-name>Premiere 4 FHD</display-name>
		<icon src="http://cutix.click/logos/ehtIUqjk_o.png" />
	</channel>
	<channel id="br#premiere-5-hd">
		<display-name>Premiere 5 FHD</display-name>
		<icon src="http://cutix.click/logos/ehtIUqjk_o.png" />
	</channel>
	<channel id="br#premiere-6">
		<display-name>Premiere 6 FHD</display-name>
		<icon src="http://cutix.click/logos/ehtIUqjk_o.png" />
	</channel>
	<channel id="br#premiere-7">
		<display-name>Premiere 7 FHD</display-name>
		<icon src="http://cutix.click/logos/ehtIUqjk_o.png" />
	</channel>
	<channel id="br#premiere-clubes-hd">
		<display-name>Premiere Clubes FHD</display-name>
		<icon src="http://cutix.click/logos/ehtIUqjk_o.png" />
	</channel>
	<channel id="BandSports.br">
		<display-name>Band Sports HD</display-name>
		<icon src="http://cutix.click/logos/9rqcPlez_o.png" />
	</channel>
	<channel id="br#bandsports-hd">
		<display-name>BandSports SD</display-name>
		<icon src="http://cutix.click/logos/9rqcPlez_o.png" />
	</channel>
	<channel id="Combate.br">
		<display-name>Combate HD</display-name>
		<icon src="http://cutix.click/logos/aEAv8G9I_t.png" />
	</channel>
	<channel id="Combate.br">
		<display-name>Combate SD</display-name>
		<icon src="http://cutix.click/logos/aEAv8G9I_t.png" />
	</channel>
	<channel id="ESPN2.br">
		<display-name>ESPN 2 HD</display-name>
		<icon src="http://cutix.click/logos/fBKlf6bd_o.png" />
	</channel>
	<channel id="ESPN2.br">
		<display-name>ESPN 2 SD</display-name>
		<icon src="http://cutix.click/logos/fBKlf6bd_o.png" />
	</channel>
	<channel id="ESPN3.br">
		<display-name>ESPN 3 HD</display-name>
		<icon src="http://cutix.click/logos/VuKcjdBl_o.png" />
	</channel>
	<channel id="ESPN3.br">
		<display-name>ESPN 3 SD</display-name>
		<icon src="http://cutix.click/logos/VuKcjdBl_o.png" />
	</channel>
	<channel id="ESPN4.br">
		<display-name>ESPN 4 HD</display-name>
		<icon src="http://cutix.click/logos/VMRDO4s8_o.png" />
	</channel>
	<channel id="ESPN4.br">
		<display-name>ESPN 4 SD</display-name>
		<icon src="http://cutix.click/logos/VMRDO4s8_o.png" />
	</channel>
	<channel id="br#espn-1">
		<display-name>ESPN Extra HD</display-name>
		<icon src="http://cutix.click/logos/lNgNYHCF_o.png" />
	</channel>
	<channel id="br#espn-1">
		<display-name>ESPN Extra SD</display-name>
		<icon src="http://cutix.click/logos/lNgNYHCF_o.png" />
	</channel>
	<channel id="br#espn-hd">
		<display-name>ESPN HD</display-name>
		<icon src="http://cutix.click/logos/lNgNYHCF_o.png" />
	</channel>
	<channel id="br#espn-hd">
		<display-name>ESPN SD</display-name>
		<icon src="http://cutix.click/logos/lNgNYHCF_o.png" />
	</channel>
	<channel id="ESPN5.br">
		<display-name>ESPN 5 SD</display-name>
		<icon src="http://cutix.click/logos/o1z6vi4C_t.png" />
	</channel>
	<channel id="ESPN5.br">
		<display-name>ESPN 5 HD</display-name>
		<icon src="http://cutix.click/logos/o1z6vi4C_t.png" />
	</channel>
	<channel id="BandSports.br">
		<display-name>Band Sports FHD</display-name>
		<icon src="http://cutix.click/logos/9rqcPlez_o.png" />
	</channel>
	<channel id="Combate.br">
		<display-name>Combate FHD</display-name>
		<icon src="http://cutix.click/logos/aEAv8G9I_t.png" />
	</channel>
	<channel id="br#espn-hd">
		<display-name>ESPN FHD</display-name>
		<icon src="http://cutix.click/logos/lNgNYHCF_o.png" />
	</channel>
	<channel id="ESPN2.br">
		<display-name>ESPN 2 FHD</display-name>
		<icon src="http://cutix.click/logos/fBKlf6bd_o.png" />
	</channel>
	<channel id="ESPN3.br">
		<display-name>ESPN 3 FHD</display-name>
		<icon src="http://cutix.click/logos/VuKcjdBl_o.png" />
	</channel>
	<channel id="ESPN4.br">
		<display-name>ESPN 4 FHD</display-name>
		<icon src="http://cutix.click/logos/VMRDO4s8_o.png" />
	</channel>
	<channel id="br#espn-1">
		<display-name>ESPN Extra FHD</display-name>
		<icon src="http://cutix.click/logos/lNgNYHCF_o.png" />
	</channel>
	<channel id="ESPN5.br">
		<display-name>ESPN 5 FHD</display-name>
		<icon src="http://cutix.click/logos/o1z6vi4C_t.png" />
	</channel>
	<channel id="AgroMais.br">
		<display-name>Agro+ HD</display-name>
		<icon src="http://cutix.click/logos/Ni1fDg0.png" />
	</channel>
	<channel id="AgroMais.br">
		<display-name>Agro+ SD</display-name>
		<icon src="http://cutix.click/logos/Ni1fDg0.png" />
	</channel>
	<channel id="br#canal-brasil-hd">
		<display-name>Canal Brasil HD</display-name>
		<icon src="http://cutix.click/logos/QXucCN9Z_o.png" />
	</channel>
	<channel id="CanaldoBoi.br">
		<display-name>Canal do Boi HD</display-name>
		<icon src="http://cutix.click/logos/BUPLXmht_o.png" />
	</channel>
	<channel id="CanaldoBoi.br">
		<display-name>Canal do Boi SD</display-name>
		<icon src="http://cutix.click/logos/BUPLXmht_o.png" />
	</channel>
	<channel id="CanalRural.br">
		<display-name>Canal Rural</display-name>
		<icon src="http://cutix.click/logos/ThNKJt58_o.png" />
	</channel>
	<channel id="CanalRural.br">
		<display-name>Canal Rural</display-name>
		<icon src="http://cutix.click/logos/ThNKJt58_o.png" />
	</channel>
	<channel id="br#cnt">
		<display-name>CNT SD</display-name>
		<icon src="https://imagizer.imageshack.com/v2/150x100q90/924/KhVRFe.png" />
	</channel>
	<channel id="br#futura-hd">
		<display-name>Futura HD</display-name>
		<icon src="http://cutix.click/logos/vXiCLvWm_o.png" />
	</channel>
	<channel id="br#rede-brasil-hd">
		<display-name>Rede Brasil SD</display-name>
		<icon src="http://cutix.click/logos/6pGNBtM1_o.png" />
	</channel>
	<channel id="br#rede-vida-porto-alegre">
		<display-name>REDE TV PAMPA PORTO ALEGRE</display-name>
		<icon src="http://cutix.click/logos/j7zOSJZZ_o.png" />
	</channel>
	<channel id="br#rede-tv-hd">
		<display-name>REDE TV SP</display-name>
		<icon src="http://cutix.click/logos/j7zOSJZZ_o.png" />
	</channel>
	<channel id="br#rede-tv-hd">
		<display-name>RedeTV! HD</display-name>
		<icon src="http://cutix.click/logos/j7zOSJZZ_o.png" />
	</channel>
	<channel id="br#rede-tv-hd">
		<display-name>RedeTV! SD</display-name>
		<icon src="http://cutix.click/logos/j7zOSJZZ_o.png" />
	</channel>
	<channel id="br#terra-viva-hd">
		<display-name>Terra Viva HD</display-name>
	</channel>
	<channel id="br#terra-viva-hd">
		<display-name>Terra Viva SD</display-name>
		<icon src="https://imagizer.imageshack.com/v2/320x240q90/924/BBdTfu.png" />
	</channel>
	<channel id="br#tv-brasil-hd">
		<display-name>TV Brasil HD</display-name>
		<icon src="http://cutix.click/logos/cym8W2U3_o.png" />
	</channel>
	<channel id="br#tv-brasil-hd">
		<display-name>TV Brasil SD</display-name>
		<icon src="http://cutix.click/logos/cym8W2U3_o.png" />
	</channel>
	<channel id="br#cultura-hd">
		<display-name>TV Cultura HD</display-name>
		<icon src="http://cutix.click/logos/zJFvQYst_o.png" />
	</channel>
	<channel id="br#cultura-hd">
		<display-name>TV Cultura SD</display-name>
		<icon src="http://cutix.click/logos/zJFvQYst_o.png" />
	</channel>
	<channel id="br#tv-camara-hd">
		<display-name>TV Câmara</display-name>
	</channel>
	<channel id="br#tv-gazeta">
		<display-name>TV Gazeta HD</display-name>
		<icon src="http://cutix.click/logos/vK6Bkhet_o.png" />
	</channel>
	<channel id="br#tv-gazeta">
		<display-name>TV Gazeta SD</display-name>
		<icon src="http://cutix.click/logos/vK6Bkhet_o.png" />
	</channel>
	<channel id="br#tv-justica">
		<display-name>TV Justiça</display-name>
		<icon src="http://cutix.click/logos/czAv1STM_o.png" />
	</channel>
	<channel id="br#tv-senado-hd">
		<display-name>TV Senado SD</display-name>
		<icon src="http://cutix.click/logos/1ZP3xOX6_o.png" />
	</channel>
	<channel id="br#tv-brasil-hd">
		<display-name>TVE Brasil SD</display-name>
		<icon src="https://imagizer.imageshack.com/v2/320x240q90/923/XF7jhD.png" />
	</channel>
	<channel id="TVCulturaNacional.br">
		<display-name>TV CULTURA PARA</display-name>
		<icon src="http://cutix.click/logos/zJFvQYst_o.png" />
	</channel>
	<channel id="TVPampa.br">
		<display-name>TV Pampa HD</display-name>
	</channel>
	<channel id="br#cnt">
		<display-name>CNT HD</display-name>
		<icon src="https://imagizer.imageshack.com/v2/150x100q90/924/KhVRFe.png" />
	</channel>
	<channel id="br#tv-senado-hd">
		<display-name>TV Senado HD</display-name>
		<icon src="http://cutix.click/logos/1ZP3xOX6_o.png" />
	</channel>
	<channel id="br#tv-camara-hd">
		<display-name>TV Câmara HD</display-name>
	</channel>
	<channel id="AgroMais.br">
		<display-name>Agro+ FHD</display-name>
		<icon src="http://cutix.click/logos/Ni1fDg0.png" />
	</channel>
	<channel id="CanaldoBoi.br">
		<display-name>Canal do Boi FHD</display-name>
		<icon src="http://cutix.click/logos/BUPLXmht_o.png" />
	</channel>
	<channel id="br#rede-tv-hd">
		<display-name>RedeTV! FHD</display-name>
		<icon src="http://cutix.click/logos/j7zOSJZZ_o.png" />
	</channel>
	<channel id="br#tv-brasil-hd">
		<display-name>TV Brasil FHD</display-name>
		<icon src="http://cutix.click/logos/cym8W2U3_o.png" />
	</channel>
	<channel id="br#cultura-hd">
		<display-name>TV Cultura FHD</display-name>
		<icon src="http://cutix.click/logos/zJFvQYst_o.png" />
	</channel>
	<channel id="br#rede-brasil-hd">
		<display-name>REDE BRASIL FHD</display-name>
		<icon src="http://cutix.click/logos/6pGNBtM1_o.png" />
	</channel>
	<channel id="CartoonNetwork.br">
		<display-name>Cartoon Network HD</display-name>
		<icon src="http://cutix.click/logos/eDR5nSJt_o.png" />
	</channel>
	<channel id="CartoonNetwork.br">
		<display-name>Cartoon Network SD</display-name>
		<icon src="http://cutix.click/logos/eDR5nSJt_o.png" />
	</channel>
	<channel id="Cartoonito.br">
		<display-name>Cartoonito HD</display-name>
		<icon src="http://cutix.click/logos/M5t2la1T_o.png" />
	</channel>
	<channel id="Cartoonito.br">
		<display-name>Cartoonito SD</display-name>
		<icon src="http://cutix.click/logos/M5t2la1T_o.png" />
	</channel>
	<channel id="br#gloob-hd">
		<display-name>Gloob HD</display-name>
		<icon src="http://cutix.click/logos/Tstj3Kb1_o.png" />
	</channel>
	<channel id="br#gloobinho-hd">
		<display-name>Gloobinho HD</display-name>
		<icon src="http://cutix.click/logos/Jja9jFa4_o.png" />
	</channel>
	<channel id="br#gloobinho-hd">
		<display-name>Gloobinho SD</display-name>
		<icon src="http://cutix.click/logos/Jja9jFa4_o.png" />
	</channel>
	<channel id="br#nick-jr-hd">
		<display-name>Nick Jr. HD</display-name>
		<icon src="http://cutix.click/logos/KAxqeqfQ_o.png" />
	</channel>
	<channel id="br#nick-jr-hd">
		<display-name>Nick Jr. SD</display-name>
		<icon src="http://cutix.click/logos/KAxqeqfQ_o.png" />
	</channel>
	<channel id="Nickelodeon.br">
		<display-name>Nickelodeon HD</display-name>
		<icon src="http://cutix.click/logos/7iKcubbm_o.png" />
	</channel>
	<channel id="Nickelodeon.br">
		<display-name>Nickelodeon SD</display-name>
		<icon src="http://cutix.click/logos/7iKcubbm_o.png" />
	</channel>
	<channel id="br#tv-ra-tim-bum-hd">
		<display-name>TV Rá Tim Bum HD</display-name>
	</channel>
	<channel id="br#tv-ra-tim-bum-hd">
		<display-name>TV Rá Tim Bum SD</display-name>
		<icon src="http://images.mi.tv/channels/br_ra-tim-bum-1_m.png" />
	</channel>
	<channel id="ZooMoo.sg">
		<display-name>ZooMoo HD</display-name>
		<icon src="http://cutix.click/logos/JAdbMuOO_o.png" />
	</channel>
	<channel id="ZooMoo.sg">
		<display-name>ZooMoo SD</display-name>
		<icon src="http://cutix.click/logos/JAdbMuOO_o.png" />
	</channel>
	<channel id="CartoonNetwork.br">
		<display-name>Cartoon Network FHD</display-name>
		<icon src="http://cutix.click/logos/eDR5nSJt_o.png" />
	</channel>
	<channel id="Cartoonito.br">
		<display-name>Cartoonito FHD</display-name>
		<icon src="http://cutix.click/logos/M5t2la1T_o.png" />
	</channel>
	<channel id="br#gloob-hd">
		<display-name>Gloob FHD</display-name>
		<icon src="http://cutix.click/logos/Tstj3Kb1_o.png" />
	</channel>
	<channel id="br#gloobinho-hd">
		<display-name>Gloobinho FHD</display-name>
		<icon src="http://cutix.click/logos/Jja9jFa4_o.png" />
	</channel>
	<channel id="br#nick-jr-hd">
		<display-name>Nick Jr. FHD</display-name>
		<icon src="http://cutix.click/logos/KAxqeqfQ_o.png" />
	</channel>
	<channel id="Nickelodeon.br">
		<display-name>Nickelodeon FHD</display-name>
		<icon src="http://cutix.click/logos/7iKcubbm_o.png" />
	</channel>
	<channel id="br#tv-ra-tim-bum-hd">
		<display-name>TV Rá Tim Bum FHD</display-name>
		<icon src="http://images.mi.tv/channels/br_ra-tim-bum-1_m.png" />
	</channel>
	<channel id="br#comedy-central-hd">
		<display-name>Comedy Central HD</display-name>
		<icon src="http://cutix.click/logos/jG8y2vZz_o.png" />
	</channel>
	<channel id="br#comedy-central-hd">
		<display-name>Comedy Central SD</display-name>
		<icon src="http://cutix.click/logos/jG8y2vZz_o.png" />
	</channel>
	<channel id="br#curta-hd">
		<display-name>Curta! HD</display-name>
		<icon src="http://cutix.click/logos/GGeKPjE5_o.png" />
	</channel>
	<channel id="br#curta-hd">
		<display-name>Curta! SD</display-name>
		<icon src="http://cutix.click/logos/GGeKPjE5_o.png" />
	</channel>
	<channel id="br#e-hd">
		<display-name>E! HD</display-name>
		<icon src="http://cutix.click/logos/GwAHxYAY_o.png" />
	</channel>
	<channel id="br#e-hd">
		<display-name>E! SD</display-name>
		<icon src="http://cutix.click/logos/GwAHxYAY_o.png" />
	</channel>
	<channel id="FashionTV.br">
		<display-name>Fashion TV HD</display-name>
	</channel>
	<channel id="FashionTV.br">
		<display-name>Fashion TV SD</display-name>
		<icon src="https://imagizer.imageshack.com/v2/640x480q90/924/EPVUsW.png" />
	</channel>
	<channel id="FoodNetwork.br">
		<display-name>Food Network HD</display-name>
		<icon src="http://cutix.click/logos/4zCM4OKh_o.png" />
	</channel>
	<channel id="FoodNetwork.br">
		<display-name>Food Network SD</display-name>
		<icon src="http://cutix.click/logos/4zCM4OKh_o.png" />
	</channel>
	<channel id="br#futura-hd">
		<display-name>Futura SD</display-name>
		<icon src="http://cutix.click/logos/vXiCLvWm_o.png" />
	</channel>
	<channel id="br#gnt-hd">
		<display-name>GNT HD</display-name>
		<icon src="http://cutix.click/logos/5f9bb97ed5f47090caf1d3fc1fafc871.png" />
	</channel>
	<channel id="br#gnt-hd">
		<display-name>GNT SD</display-name>
		<icon src="http://cutix.click/logos/5f9bb97ed5f47090caf1d3fc1fafc871.png" />
	</channel>
	<channel id="br#hgtv-hd">
		<display-name>HGTV HD</display-name>
		<icon src="http://cutix.click/logos/bjOlE3PT_o.png" />
	</channel>
	<channel id="br#hgtv-hd">
		<display-name>HGTV SD</display-name>
		<icon src="http://cutix.click/logos/bjOlE3PT_o.png" />
	</channel>
	<channel id="br#lifetime-hd">
		<display-name>Lifetime HD</display-name>
		<icon src="http://cutix.click/logos/VCa28J5B_o.png" />
	</channel>
	<channel id="br#lifetime-hd">
		<display-name>Lifetime SD</display-name>
		<icon src="http://cutix.click/logos/VCa28J5B_o.png" />
	</channel>
	<channel id="br#multishow-hd">
		<display-name>Multishow HD</display-name>
		<icon src="http://cutix.click/logos/nymcDeFf_o.png" />
	</channel>
	<channel id="br#multishow-hd">
		<display-name>Multishow SD</display-name>
		<icon src="http://cutix.click/logos/nymcDeFf_o.png" />
	</channel>
	<channel id="br#off-hd">
		<display-name>OFF HD</display-name>
		<icon src="http://cutix.click/logos/fPKyPhuQ_o.png" />
	</channel>
	<channel id="br#off-hd">
		<display-name>OFF SD</display-name>
		<icon src="http://cutix.click/logos/fPKyPhuQ_o.png" />
	</channel>
	<channel id="br#tlc-hd">
		<display-name>TLC SD</display-name>
		<icon src="http://cutix.click/logos/WAMcsVqF_o.png" />
	</channel>
	<channel id="TraceBrazuca.fr">
		<display-name>Trace Brazuca HD</display-name>
		<icon src="http://cutix.click/logos/iCHoGbv.png" />
	</channel>
	<channel id="TraceBrazuca.fr">
		<display-name>Trace Brazuca SD</display-name>
		<icon src="http://cutix.click/logos/iCHoGbv.png" />
	</channel>
	<channel id="br#travel-box-brazil-hd">
		<display-name>Travel Box Brazil HD</display-name>
		<icon src="http://cutix.click/logos/E51c1T3H_o.png" />
	</channel>
	<channel id="br#travel-box-brazil-hd">
		<display-name>Travel Box Brazil SD</display-name>
		<icon src="http://cutix.click/logos/E51c1T3H_o.png" />
	</channel>
	<channel id="br#viva-hd">
		<display-name>Viva HD</display-name>
		<icon src="http://cutix.click/logos/zzB9ZARC_o.png" />
	</channel>
	<channel id="br#viva-hd">
		<display-name>Viva SD</display-name>
		<icon src="http://cutix.click/logos/zzB9ZARC_o.png" />
	</channel>
	<channel id="br#woohoo-hd">
		<display-name>Woohoo HD</display-name>
		<icon src="http://cutix.click/logos/dCzr7VQe_o.png" />
	</channel>
	<channel id="br#woohoo-hd">
		<display-name>Woohoo SD</display-name>
		<icon src="http://cutix.click/logos/dCzr7VQe_o.png" />
	</channel>
	<channel id="TraceBrazuca.fr">
		<display-name>Trace Brazuca FHD</display-name>
		<icon src="http://cutix.click/logos/iCHoGbv.png" />
	</channel>
	<channel id="br#comedy-central-hd">
		<display-name>Comedy Central FHD</display-name>
		<icon src="http://cutix.click/logos/jG8y2vZz_o.png" />
	</channel>
	<channel id="br#curta-hd">
		<display-name>Curta! FHD</display-name>
		<icon src="http://cutix.click/logos/GGeKPjE5_o.png" />
	</channel>
	<channel id="br#e-hd">
		<display-name>E! FHD</display-name>
		<icon src="http://cutix.click/logos/GwAHxYAY_o.png" />
	</channel>
	<channel id="FashionTV.br">
		<display-name>Fashion TV FHD</display-name>
		<icon src="https://imagizer.imageshack.com/v2/640x480q90/924/EPVUsW.png" />
	</channel>
	<channel id="FoodNetwork.br">
		<display-name>Food Network FHD</display-name>
		<icon src="http://cutix.click/logos/4zCM4OKh_o.png" />
	</channel>
	<channel id="br#futura-hd">
		<display-name>Futura FHD</display-name>
		<icon src="http://cutix.click/logos/vXiCLvWm_o.png" />
	</channel>
	<channel id="br#gnt-hd">
		<display-name>GNT FHD</display-name>
		<icon src="http://cutix.click/logos/5f9bb97ed5f47090caf1d3fc1fafc871.png" />
	</channel>
	<channel id="br#hgtv-hd">
		<display-name>HGTV FHD</display-name>
		<icon src="http://cutix.click/logos/bjOlE3PT_o.png" />
	</channel>
	<channel id="br#lifetime-hd">
		<display-name>Lifetime FHD</display-name>
		<icon src="http://cutix.click/logos/VCa28J5B_o.png" />
	</channel>
	<channel id="br#multishow-hd">
		<display-name>Multishow FHD</display-name>
		<icon src="http://cutix.click/logos/nymcDeFf_o.png" />
	</channel>
	<channel id="br#off-hd">
		<display-name>OFF FHD</display-name>
		<icon src="http://cutix.click/logos/fPKyPhuQ_o.png" />
	</channel>
	<channel id="br#tlc-hd">
		<display-name>TLC FHD</display-name>
		<icon src="http://cutix.click/logos/WAMcsVqF_o.png" />
	</channel>
	<channel id="br#travel-box-brazil-hd">
		<display-name>Travel Box Brazil FHD</display-name>
		<icon src="http://cutix.click/logos/E51c1T3H_o.png" />
	</channel>
	<channel id="br#viva-hd">
		<display-name>Viva FHD</display-name>
		<icon src="http://cutix.click/logos/zzB9ZARC_o.png" />
	</channel>
	<channel id="br#woohoo-hd">
		<display-name>WooHoo FHD</display-name>
		<icon src="http://cutix.click/logos/dCzr7VQe_o.png" />
	</channel>
	<channel id="SporTV2.br">
		<display-name>SporTV 2 HD</display-name>
		<icon src="http://cutix.click/logos/Tfw4QCoP_o.png" />
	</channel>
	<channel id="SporTV2.br">
		<display-name>SporTV 2 SD</display-name>
		<icon src="http://cutix.click/logos/Tfw4QCoP_o.png" />
	</channel>
	<channel id="SporTV3.br">
		<display-name>SporTV 3 HD</display-name>
		<icon src="http://cutix.click/logos/Hu9sJS2x_o.png" />
	</channel>
	<channel id="SporTV3.br">
		<display-name>SporTV 3 SD</display-name>
		<icon src="http://cutix.click/logos/Hu9sJS2x_o.png" />
	</channel>
	<channel id="br#sportv-hd">
		<display-name>SporTV SD</display-name>
		<icon src="http://cutix.click/logos/XSXzLI11_o.png" />
	</channel>
	<channel id="br#sportv-hd">
		<display-name>SporTV FHD</display-name>
		<icon src="http://cutix.click/logos/XSXzLI11_o.png" />
	</channel>
	<channel id="SporTV2.br">
		<display-name>SporTV 2 FHD</display-name>
		<icon src="http://cutix.click/logos/Tfw4QCoP_o.png" />
	</channel>
	<channel id="SporTV3.br">
		<display-name>SporTV 3 FHD</display-name>
		<icon src="http://cutix.click/logos/Hu9sJS2x_o.png" />
	</channel>
	<channel id="BandNews.br">
		<display-name>Band News HD</display-name>
		<icon src="http://cutix.click/logos/eMhzFOQ7_o.png" />
	</channel>
	<channel id="BandNews.br">
		<display-name>Band News SD</display-name>
		<icon src="http://cutix.click/logos/eMhzFOQ7_o.png" />
	</channel>
	<channel id="br#bloomberg">
		<display-name>BLOOMBERG HD</display-name>
	</channel>
	<channel id="br#bloomberg">
		<display-name>BLOOMBERG SD</display-name>
	</channel>
	<channel id="br#cnn-brasil-1">
		<display-name>CNN - Brasil HD</display-name>
		<icon src="http://cutix.click/logos/SO9zouzi_o.png" />
	</channel>
	<channel id="br#cnn-brasil-1">
		<display-name>CNN - Brasil SD</display-name>
		<icon src="http://cutix.click/logos/SO9zouzi_o.png" />
	</channel>
	<channel id="br#globo-news-hd">
		<display-name>Globo News HD</display-name>
		<icon src="http://cutix.click/logos/vK6Bkhet_o.png" />
	</channel>
	<channel id="br#globo-news-hd">
		<display-name>Globo News SD</display-name>
		<icon src="http://cutix.click/logos/vK6Bkhet_o.png" />
	</channel>
	<channel id="JPNews.br">
		<display-name>Jovem Pan NEWS HD</display-name>
		<icon src="http://cutix.click/logos/pi0nPXBd_o.png" />
	</channel>
	<channel id="JPNews.br">
		<display-name>Jovem Pan News SD</display-name>
		<icon src="http://cutix.click/logos/pi0nPXBd_o.png" />
	</channel>
	<channel id="br#record-news-hd">
		<display-name>Record News HD</display-name>
		<icon src="http://cutix.click/logos/889h5lwp_o.png" />
	</channel>
	<channel id="br#record-news-hd">
		<display-name>Record News SD</display-name>
		<icon src="http://cutix.click/logos/889h5lwp_o.png" />
	</channel>
	<channel id="br#cnn-en-espanol-hd">
		<display-name>CNN en Español HD</display-name>
	</channel>
	<channel id="BandNews.br">
		<display-name>Band News FHD</display-name>
		<icon src="http://cutix.click/logos/eMhzFOQ7_o.png" />
	</channel>
	<channel id="br#cnn-brasil-1">
		<display-name>CNN - Brasil FHD</display-name>
		<icon src="http://cutix.click/logos/SO9zouzi_o.png" />
	</channel>
	<channel id="br#globo-news-hd">
		<display-name>Globo News FHD</display-name>
		<icon src="http://cutix.click/logos/Gxf9fSIm_o.png" />
	</channel>
	<channel id="JPNews.br">
		<display-name>Jovem Pan News FHD</display-name>
		<icon src="http://cutix.click/logos/pi0nPXBd_o.png" />
	</channel>
	<channel id="br#record-news-hd">
		<display-name>Record News FHD</display-name>
		<icon src="http://cutix.click/logos/889h5lwp_o.png" />
	</channel>
	<channel id="BoasNovas.br">
		<display-name>Boas Novas</display-name>
		<icon src="https://imagizer.imageshack.com/v2/640x480q90/922/Aco1pK.png" />
	</channel>
	<channel id="br#canc-o-nova-hd">
		<display-name>Canção Nova HD</display-name>
		<icon src="http://cutix.click/logos/Ttut6Z9.png" />
	</channel>
	<channel id="br#rede-familia-hd">
		<display-name>Rede Família HD</display-name>
	</channel>
	<channel id="br#rede-gospel-hd">
		<display-name>Rede Gospel</display-name>
		<icon src="http://cutix.click/logos/Cy9vmbq.png" />
	</channel>
	<channel id="br#rede-vida-hd">
		<display-name>Rede Vida HD</display-name>
		<icon src="http://cutix.click/logos/CrngiGf.png" />
	</channel>
	<channel id="br#tv-aparecida-hd">
		<display-name>TV Aparecida HD</display-name>
		<icon src="http://cutix.click/logos/28VtCwQ.png" />
	</channel>
	<channel id="br#tv-aparecida-hd">
		<display-name>TV Aparecida SD</display-name>
		<icon src="http://cutix.click/logos/28VtCwQ.png" />
	</channel>
	<channel id="br#tv-mundial">
		<display-name>TV Mundial</display-name>
	</channel>
	<channel id="br#tv-novo-tempo-hd">
		<display-name>TV Novo Tempo HD</display-name>
		<icon src="http://cutix.click/logos/SV7cIVX.png" />
	</channel>
	<channel id="br#tv-aparecida-hd">
		<display-name>TV APARECIDA FHD</display-name>
		<icon src="http://cutix.click/logos/28VtCwQ.png" />
	</channel>
	<channel id="Bis.br">
		<display-name>BIS HD</display-name>
		<icon src="http://cutix.click/logos/I3Vp10VS_o.png" />
	</channel>
	<channel id="Bis.br">
		<display-name>BIS SD</display-name>
		<icon src="http://cutix.click/logos/I3Vp10VS_o.png" />
	</channel>
	<channel id="br#mtv">
		<display-name>MTV HD</display-name>
		<icon src="http://cutix.click/logos/b0rSYyrV_o.png" />
	</channel>
	<channel id="MTVLive.uk">
		<display-name>MTV LIVE HD</display-name>
		<icon src="http://cutix.click/logos/VtQl226b_o.png" />
	</channel>
	<channel id="MTVLive.uk">
		<display-name>MTV LIVE SD</display-name>
		<icon src="http://cutix.click/logos/VtQl226b_o.png" />
	</channel>
	<channel id="MTV00s.uk">
		<display-name>MTV s 00 HD</display-name>
		<icon src="http://cutix.click/logos/b0rSYyrV_o.png" />
	</channel>
	<channel id="MTV00s.uk">
		<display-name>MTV s 00 SD</display-name>
		<icon src="http://cutix.click/logos/b0rSYyrV_o.png" />
	</channel>
	<channel id="br#mtv">
		<display-name>MTV SD</display-name>
		<icon src="http://cutix.click/logos/b0rSYyrV_o.png" />
	</channel>
	<channel id="MusicBoxBrazil.br">
		<display-name>Music Box Brazil HD</display-name>
		<icon src="http://cutix.click/logos/HImntNSq_o.png" />
	</channel>
	<channel id="MusicBoxBrazil.br">
		<display-name>Music Box Brazil SD</display-name>
		<icon src="http://cutix.click/logos/HImntNSq_o.png" />
	</channel>
	<channel id="Bis.br">
		<display-name>BIS FHD</display-name>
		<icon src="http://cutix.click/logos/I3Vp10VS_o.png" />
	</channel>
	<channel id="br#mtv">
		<display-name>MTV FHD</display-name>
		<icon src="http://cutix.click/logos/b0rSYyrV_o.png" />
	</channel>
	<channel id="MTVLive.uk">
		<display-name>MTV LIVE FHD</display-name>
		<icon src="http://cutix.click/logos/VtQl226b_o.png" />
	</channel>
	<channel id="MTV00s.uk">
		<display-name>MTV s 00 FHD</display-name>
		<icon src="http://cutix.click/logos/b0rSYyrV_o.png" />
	</channel>
	<channel id="MusicBoxBrazil.br">
		<display-name>Music Box Brazil FHD</display-name>
		<icon src="http://cutix.click/logos/HImntNSq_o.png" />
	</channel>
	<channel id="DiscoveryChannel.br">
		<display-name>Discovery Channel HD</display-name>
		<icon src="http://cutix.click/logos/mduPALwC_o.png" />
	</channel>
	<channel id="DiscoveryChannel.br">
		<display-name>Discovery Channel SD</display-name>
		<icon src="http://cutix.click/logos/mduPALwC_o.png" />
	</channel>
	<channel id="br#discovery-home-health-hd">
		<display-name>Discovery H&amp;H HD</display-name>
		<icon src="http://cutix.click/logos/FNTee0Ku_o.png" />
	</channel>
	<channel id="DiscoveryHomeHealth.br">
		<display-name>Discovery H&amp;H SD</display-name>
		<icon src="http://cutix.click/logos/FNTee0Ku_o.png" />
	</channel>
	<channel id="br#discovery-kids-hd">
		<display-name>Discovery Kids HD</display-name>
		<icon src="http://cutix.click/logos/vbYb7Xkr_o.png" />
	</channel>
	<channel id="br#discovery-kids-hd">
		<display-name>Discovery Kids SD</display-name>
		<icon src="http://cutix.click/logos/vbYb7Xkr_o.png" />
	</channel>
	<channel id="br#discovery-science-hd">
		<display-name>Discovery Science HD</display-name>
		<icon src="http://cutix.click/logos/DFGKm8Cs_o.png" />
	</channel>
	<channel id="br#discovery-science-hd">
		<display-name>Discovery Science SD</display-name>
		<icon src="http://cutix.click/logos/DFGKm8Cs_o.png" />
	</channel>
	<channel id="DiscoveryTheater.br">
		<display-name>Discovery Theater HD</display-name>
		<icon src="http://cutix.click/logos/jCQuyI45_o.png" />
	</channel>
	<channel id="DiscoveryTheater.br">
		<display-name>Discovery Theater SD</display-name>
		<icon src="http://cutix.click/logos/jCQuyI45_o.png" />
	</channel>
	<channel id="br#discovery-turbo-hd">
		<display-name>Discovery Turbo HD</display-name>
		<icon src="http://cutix.click/logos/oT03W6tc_o.png" />
	</channel>
	<channel id="br#discovery-turbo-hd">
		<display-name>Discovery Turbo SD</display-name>
		<icon src="http://cutix.click/logos/oT03W6tc_o.png" />
	</channel>
	<channel id="DiscoveryWorld.br">
		<display-name>Discovery World HD</display-name>
		<icon src="http://cutix.click/logos/47GmQnDN_o.png" />
	</channel>
	<channel id="DiscoveryWorld.br">
		<display-name>Discovery World SD</display-name>
		<icon src="http://cutix.click/logos/47GmQnDN_o.png" />
	</channel>
	<channel id="InvestigationDiscovery.br">
		<display-name>ID - Investigation Discovery HD</display-name>
		<icon src="http://cutix.click/logos/nkyXN4Yw_o.png" />
	</channel>
	<channel id="InvestigationDiscovery.br">
		<display-name>ID - Investigation Discovery SD</display-name>
		<icon src="http://cutix.click/logos/nkyXN4Yw_o.png" />
	</channel>
	<channel id="DiscoveryChannel.br">
		<display-name>Discovery Channel FHD</display-name>
		<icon src="http://cutix.click/logos/mduPALwC_o.png" />
	</channel>
	<channel id="DiscoveryHomeHealth.br">
		<display-name>Discovery H&amp;H FHD</display-name>
		<icon src="http://cutix.click/logos/FNTee0Ku_o.png" />
	</channel>
	<channel id="br#discovery-science-hd">
		<display-name>Discovery Science FHD</display-name>
		<icon src="http://cutix.click/logos/DFGKm8Cs_o.png" />
	</channel>
	<channel id="DiscoveryTheater.br">
		<display-name>Discovery Theater FHD</display-name>
		<icon src="http://cutix.click/logos/jCQuyI45_o.png" />
	</channel>
	<channel id="br#discovery-turbo-hd">
		<display-name>Discovery Turbo FHD</display-name>
		<icon src="http://cutix.click/logos/oT03W6tc_o.png" />
	</channel>
	<channel id="DiscoveryWorld.br">
		<display-name>Discovery World FHD</display-name>
		<icon src="http://cutix.click/logos/47GmQnDN_o.png" />
	</channel>
	<channel id="InvestigationDiscovery.br">
		<display-name>ID - Investigation Discovery FHD</display-name>
		<icon src="http://cutix.click/logos/nkyXN4Yw_o.png" />
	</channel>
	<channel id="br#discovery-kids-hd">
		<display-name>Discovery Kids FHD</display-name>
		<icon src="http://cutix.click/logos/vbYb7Xkr_o.png" />
	</channel>
</tv>